aedev/git_repo_manager/__init__.py
aedev/git_repo_manager/__main__.py
aedev_git_repo_manager-0.3.102.dist-info/licenses/LICENSE.md
aedev_git_repo_manager-0.3.102.dist-info/METADATA
aedev_git_repo_manager-0.3.102.dist-info/WHEEL
aedev_git_repo_manager-0.3.102.dist-info/entry_points.txt
aedev_git_repo_manager-0.3.102.dist-info/top_level.txt
aedev_git_repo_manager-0.3.102.dist-info/zip-safe
aedev_git_repo_manager-0.3.102.dist-info/RECORD
